src/app/cli.py
src/app/css/style.css
src/app/modules/api.py
src/app/modules/common.py
src/app/modules/logger.py
python_xdoc-0.1.1.dist-info/LICENSE
python_xdoc-0.1.1.dist-info/METADATA
python_xdoc-0.1.1.dist-info/WHEEL
python_xdoc-0.1.1.dist-info/entry_points.txt
python_xdoc-0.1.1.dist-info/RECORD
